README.md
setup.py
ch_frb_wview/__init__.py
ch_frb_wview/chime_frb_operations.py
ch_frb_wview/chime_frb_operations_interface.py
ch_frb_wview/chlog_database.py
ch_frb_wview/cnc_client.py
ch_frb_wview/cnc_ssh.py
ch_frb_wview/rpc_client.py
ch_frb_wview/webapp.py
ch_frb_wview_test_2.egg-info/PKG-INFO
ch_frb_wview_test_2.egg-info/SOURCES.txt
ch_frb_wview_test_2.egg-info/dependency_links.txt
ch_frb_wview_test_2.egg-info/requires.txt
ch_frb_wview_test_2.egg-info/top_level.txt